dariah_topics
