Metadata-Version: 1.1
Name: dariah-topics-light
Version: 1.4
Summary: DARIAH Topic Modelling
Home-page: UNKNOWN
Author: DARIAH-DE Wuerzburg Group
Author-email: pielstroem@biozentrum.uni-wuerzburg.de
License: UNKNOWN
Platform: UNKNOWN
Classifier: Development Status :: 3 - Alpha
Classifier: Programming Language :: Python :: 3.6
